learntorank/__init__.py
learntorank/_modidx.py
learntorank/evaluation.py
learntorank/ml.py
learntorank/passage.py
learntorank/query.py
learntorank/ranking.py
learntorank/stats.py
learntorank/text.py
learntorank-0.0.21.dist-info/LICENSE
learntorank-0.0.21.dist-info/METADATA
learntorank-0.0.21.dist-info/WHEEL
learntorank-0.0.21.dist-info/entry_points.txt
learntorank-0.0.21.dist-info/top_level.txt
learntorank-0.0.21.dist-info/RECORD
