Metadata-Version: 2.1
Name: learntorank
Version: 0.0.21
Summary: Learning to rank library
Home-page: https://github.com/vespa-engine/learntorank/
Author: tmartins
Author-email: tmartins@yahooinc.com
License: Apache Software License 2.0
Keywords: nbdev
Classifier: Development Status :: 3 - Alpha
Classifier: Intended Audience :: Developers
Classifier: Natural Language :: English
Classifier: Programming Language :: Python :: 3.8
Classifier: Programming Language :: Python :: 3.9
Classifier: Programming Language :: Python :: 3.10
Classifier: License :: OSI Approved :: Apache Software License
Requires-Python: >=3.8
License-File: LICENSE
Requires-Dist: fastcore
Requires-Dist: pandas
Requires-Dist: ir-datasets
Requires-Dist: pyvespa
Requires-Dist: tensorflow
Requires-Dist: tensorflow-ranking
Requires-Dist: keras-tuner
Requires-Dist: onnxruntime
Requires-Dist: transformers
Requires-Dist: torch (<1.13)
Provides-Extra: dev
Requires-Dist: matplotlib (<3.6) ; extra == 'dev'
Requires-Dist: plotnine ; extra == 'dev'
